{"nodes": [{"id": "dlp_user_ui_build_rs", "label": "build.rs", "file_type": "code", "source_file": "dlp-user-ui\\build.rs", "source_location": "L1"}, {"id": "build_main", "label": "main()", "file_type": "code", "source_file": "dlp-user-ui\\build.rs", "source_location": "L1"}, {"id": "build_write_ico", "label": "write_ico()", "file_type": "code", "source_file": "dlp-user-ui\\build.rs", "source_location": "L17"}], "edges": [{"source": "dlp_user_ui_build_rs", "target": "build_main", "relation": "contains", "confidence": "EXTRACTED", "source_file": "dlp-user-ui\\build.rs", "source_location": "L1", "weight": 1.0}, {"source": "dlp_user_ui_build_rs", "target": "build_write_ico", "relation": "contains", "confidence": "EXTRACTED", "source_file": "dlp-user-ui\\build.rs", "source_location": "L17", "weight": 1.0}, {"source": "build_main", "target": "build_write_ico", "relation": "calls", "confidence": "EXTRACTED", "source_file": "dlp-user-ui\\build.rs", "source_location": "L2", "weight": 1.0}]}