{"nodes": [{"id": "dlp_server_src_policy_sync_rs", "label": "policy_sync.rs", "file_type": "code", "source_file": "dlp-server\\src\\policy_sync.rs", "source_location": "L1"}, {"id": "policy_sync_policysyncer", "label": "PolicySyncer", "file_type": "code", "source_file": "dlp-server\\src\\policy_sync.rs", "source_location": "L15"}, {"id": "policy_sync_syncerror", "label": "SyncError", "file_type": "code", "source_file": "dlp-server\\src\\policy_sync.rs", "source_location": "L24"}, {"id": "policy_sync_policysyncer_from_env", "label": ".from_env()", "file_type": "code", "source_file": "dlp-server\\src\\policy_sync.rs", "source_location": "L51"}, {"id": "policy_sync_policysyncer_sync_policy", "label": ".sync_policy()", "file_type": "code", "source_file": "dlp-server\\src\\policy_sync.rs", "source_location": "L79"}, {"id": "policy_sync_policysyncer_delete_policy", "label": ".delete_policy()", "file_type": "code", "source_file": "dlp-server\\src\\policy_sync.rs", "source_location": "L136"}, {"id": "policy_sync_test_empty_replicas", "label": "test_empty_replicas()", "file_type": "code", "source_file": "dlp-server\\src\\policy_sync.rs", "source_location": "L190"}, {"id": "policy_sync_test_parse_replicas", "label": "test_parse_replicas()", "file_type": "code", "source_file": "dlp-server\\src\\policy_sync.rs", "source_location": "L199"}], "edges": [{"source": "dlp_server_src_policy_sync_rs", "target": "policy", "relation": "imports_from", "confidence": "EXTRACTED", "source_file": "dlp-server\\src\\policy_sync.rs", "source_location": "L7", "weight": 1.0}, {"source": "dlp_server_src_policy_sync_rs", "target": "client", "relation": "imports_from", "confidence": "EXTRACTED", "source_file": "dlp-server\\src\\policy_sync.rs", "source_location": "L8", "weight": 1.0}, {"source": "dlp_server_src_policy_sync_rs", "target": "policy_sync_policysyncer", "relation": "contains", "confidence": "EXTRACTED", "source_file": "dlp-server\\src\\policy_sync.rs", "source_location": "L15", "weight": 1.0}, {"source": "dlp_server_src_policy_sync_rs", "target": "policy_sync_syncerror", "relation": "contains", "confidence": "EXTRACTED", "source_file": "dlp-server\\src\\policy_sync.rs", "source_location": "L24", "weight": 1.0}, {"source": "policy_sync_policysyncer", "target": "policy_sync_policysyncer_from_env", "relation": "method", "confidence": "EXTRACTED", "source_file": "dlp-server\\src\\policy_sync.rs", "source_location": "L51", "weight": 1.0}, {"source": "policy_sync_policysyncer", "target": "policy_sync_policysyncer_sync_policy", "relation": "method", "confidence": "EXTRACTED", "source_file": "dlp-server\\src\\policy_sync.rs", "source_location": "L79", "weight": 1.0}, {"source": "policy_sync_policysyncer", "target": "policy_sync_policysyncer_delete_policy", "relation": "method", "confidence": "EXTRACTED", "source_file": "dlp-server\\src\\policy_sync.rs", "source_location": "L136", "weight": 1.0}, {"source": "dlp_server_src_policy_sync_rs", "target": "super", "relation": "imports_from", "confidence": "EXTRACTED", "source_file": "dlp-server\\src\\policy_sync.rs", "source_location": "L187", "weight": 1.0}, {"source": "dlp_server_src_policy_sync_rs", "target": "policy_sync_test_empty_replicas", "relation": "contains", "confidence": "EXTRACTED", "source_file": "dlp-server\\src\\policy_sync.rs", "source_location": "L190", "weight": 1.0}, {"source": "dlp_server_src_policy_sync_rs", "target": "policy_sync_test_parse_replicas", "relation": "contains", "confidence": "EXTRACTED", "source_file": "dlp-server\\src\\policy_sync.rs", "source_location": "L199", "weight": 1.0}]}